{
    "model_name": "no_dropout",
    "data_variant": "simple",
    "timestamp": "20250901_151037",
    "hyperparameters": {
        "batch_size": 64,
        "optimizer": "adam",
        "learning_rate": 0.0010000000474974513,
        "epochs": 20
    },
    "val_metrics": {
        "loss": 96.70649719238281,
        "accuracy": 0.3684210479259491,
        "precision": 0.3684210479259491,
        "recall": 1.0,
        "f1": 0.5384615295007918
    },
    "history": {
        "accuracy": [
            0.373046875,
            0.373046875,
            0.373046875,
            0.373046875,
            0.373046875
        ],
        "loss": [
            106.11111450195312,
            95.99053192138672,
            86.30274200439453,
            77.3636245727539,
            68.79521179199219
        ],
        "precision_1": [
            0.373046875,
            0.373046875,
            0.373046875,
            0.373046875,
            0.373046875
        ],
        "recall_1": [
            1.0,
            1.0,
            1.0,
            1.0,
            1.0
        ],
        "val_accuracy": [
            0.3684210479259491,
            0.3684210479259491,
            0.3684210479259491,
            0.3684210479259491,
            0.3684210479259491
        ],
        "val_loss": [
            96.70649719238281,
            87.2288589477539,
            78.24591064453125,
            69.68627166748047,
            61.608551025390625
        ],
        "val_precision_1": [
            0.3684210479259491,
            0.3684210479259491,
            0.3684210479259491,
            0.3684210479259491,
            0.3684210479259491
        ],
        "val_recall_1": [
            1.0,
            1.0,
            1.0,
            1.0,
            1.0
        ]
    }
}