{"trial_id": "2", "hyperparameters": {"space": [{"class_name": "Float", "config": {"name": "learning_rate", "default": 0.0001, "conditions": [], "min_value": 0.0001, "max_value": 0.01, "step": null, "sampling": "log"}}], "values": {"learning_rate": 0.0003635889277344135}}, "metrics": {"metrics": {"accuracy": {"direction": "max", "observations": [{"value": [0.900390625], "step": 5}]}, "loss": {"direction": "min", "observations": [{"value": [0.4475823938846588], "step": 5}]}, "precision": {"direction": "max", "observations": [{"value": [0.8333333134651184], "step": 5}]}, "recall": {"direction": "max", "observations": [{"value": [0.9162303805351257], "step": 5}]}, "val_accuracy": {"direction": "max", "observations": [{"value": [0.8947368264198303], "step": 5}]}, "val_loss": {"direction": "min", "observations": [{"value": [0.462792307138443], "step": 5}]}, "val_precision": {"direction": "max", "observations": [{"value": [0.8571428656578064], "step": 5}]}, "val_recall": {"direction": "max", "observations": [{"value": [0.8571428656578064], "step": 5}]}}}, "score": 0.8947368264198303, "best_step": 5, "status": "COMPLETED", "message": null}