{
    "model_name": "build_model_with_dropout_tuner",
    "timestamp": "20250826_160812",
    "elapsed_time_sec": 3.711364507675171,
    "best_hyperparameters": {
        "dropout_rate": 0.4,
        "learning_rate": 0.0033276572881909957,
        "trained_epochs": 5,
        "batch_size": 32,
        "optimizer": "Adam",
        "final_learning_rate": 0.0033276572357863188
    },
    "environment": {
        "python_version": "3.10.12",
        "tensorflow_version": "2.19.0",
        "keras_version": "3.11.1",
        "os": "Linux-6.8.0-65-generic-x86_64-with-glibc2.35"
    },
    "history": {
        "accuracy": [
            0.955078125,
            0.9609375,
            0.962890625,
            0.96875,
            0.974609375
        ],
        "loss": [
            0.1195075660943985,
            0.14637991786003113,
            0.10829845070838928,
            0.1141006350517273,
            0.0936041921377182
        ],
        "precision": [
            0.9666666388511658,
            0.9621621370315552,
            0.967391312122345,
            0.9679144620895386,
            0.9734042286872864
        ],
        "recall": [
            0.9109947681427002,
            0.9319371581077576,
            0.9319371581077576,
            0.9476439952850342,
            0.9581151604652405
        ],
        "val_accuracy": [
            1.0,
            1.0,
            1.0,
            1.0,
            1.0
        ],
        "val_loss": [
            0.03245393931865692,
            0.023858340457081795,
            0.02489865943789482,
            0.019933925941586494,
            0.01743386499583721
        ],
        "val_precision": [
            1.0,
            1.0,
            1.0,
            1.0,
            1.0
        ],
        "val_recall": [
            1.0,
            1.0,
            1.0,
            1.0,
            1.0
        ]
    },
    "val_metrics": {
        "loss": 0.01743386499583721,
        "accuracy": 1.0,
        "precision": 1.0,
        "recall": 1.0,
        "f1_score": 0.999999995
    }
}